deptool/__init__.py
deptool/__main__.py
deptool/cmd_install.py
deptool/cmd_registries.py
deptool-0.1.0.dist-info/LICENSE.md
deptool-0.1.0.dist-info/METADATA
deptool-0.1.0.dist-info/WHEEL
deptool-0.1.0.dist-info/entry_points.txt
deptool-0.1.0.dist-info/top_level.txt
deptool-0.1.0.dist-info/RECORD
