Metadata-Version: 2.1
Name: deptool
Version: 0.1.0
Summary: A tool for installing dependencies
Author-email: Adam Morrissett <me@adamlm.com>
Project-URL: Homepage, https://github.com/adamlm/deptool
Project-URL: Bug Tracker, https://github.com/adamlm/deptool/issues
Classifier: Programming Language :: Python :: 3
Classifier: License :: OSI Approved :: MIT License
Classifier: Operating System :: OS Independent
Requires-Python: >=3.7
License-File: LICENSE.md
Requires-Dist: PyYAML
